odoo/addons/account_fiscal_year/README.rst
odoo/addons/account_fiscal_year/__init__.py
odoo/addons/account_fiscal_year/__manifest__.py
odoo/addons/account_fiscal_year/i18n/account_fiscal_year.pot
odoo/addons/account_fiscal_year/i18n/es.po
odoo/addons/account_fiscal_year/i18n/fr.po
odoo/addons/account_fiscal_year/i18n/fr_FR.po
odoo/addons/account_fiscal_year/i18n/it.po
odoo/addons/account_fiscal_year/i18n/nl.po
odoo/addons/account_fiscal_year/i18n/pt_BR.po
odoo/addons/account_fiscal_year/models/__init__.py
odoo/addons/account_fiscal_year/models/account_fiscal_year.py
odoo/addons/account_fiscal_year/models/res_company.py
odoo/addons/account_fiscal_year/readme/CONTRIBUTORS.md
odoo/addons/account_fiscal_year/readme/DESCRIPTION.md
odoo/addons/account_fiscal_year/readme/ROADMAP.md
odoo/addons/account_fiscal_year/security/account_fiscal_year_rule.xml
odoo/addons/account_fiscal_year/security/ir.model.access.csv
odoo/addons/account_fiscal_year/static/description/account_fiscal_year_form.png
odoo/addons/account_fiscal_year/static/description/icon.png
odoo/addons/account_fiscal_year/static/description/index.html
odoo/addons/account_fiscal_year/static/description/res_company_list.png
odoo/addons/account_fiscal_year/tests/__init__.py
odoo/addons/account_fiscal_year/tests/test_account_fiscal_year.py
odoo/addons/account_fiscal_year/views/account_fiscal_year_views.xml
odoo/addons/account_fiscal_year/views/res_company_views.xml
odoo_addon_account_fiscal_year-18.0.1.0.0.5.dist-info/METADATA
odoo_addon_account_fiscal_year-18.0.1.0.0.5.dist-info/WHEEL
odoo_addon_account_fiscal_year-18.0.1.0.0.5.dist-info/top_level.txt
odoo_addon_account_fiscal_year-18.0.1.0.0.5.dist-info/RECORD
