Metadata-Version: 2.1
Name: odoo-addon-account_fiscal_year
Version: 18.0.1.0.0.5
Requires-Python: >=3.10
Requires-Dist: odoo==18.0.*
Summary: Create Account Fiscal Year
Home-page: https://github.com/OCA/account-financial-tools
License: AGPL-3
Author: Agile Business Group, Camptocamp SA, Odoo Community Association (OCA)
Author-email: support@odoo-community.org
Classifier: Programming Language :: Python
Classifier: Framework :: Odoo
Classifier: Framework :: Odoo :: 18.0
Classifier: License :: OSI Approved :: GNU Affero General Public License v3
Classifier: Development Status :: 5 - Production/Stable
